Computer_Architecture/Labs/Lab06/Adnan_alqarawi/rtl/rtl.srcs/sources_1/new/data_mem.sv
`timescale 1ns / 1ps
//////////////////////////////////////////////////////////////////////////////////
// Company: 
// Engineer: 
// 
// Create Date: 12/25/2024 09:01:39 PM
// Design Name: 
// Module Name: data_mem
// Project Name: 
// Target Devices: 
// Tool Versions: 
// Description: 
// 
// Dependencies: 
// 
// Revision:
// Revision 0.01 - File Created
// Additional Comments:
// 
//////////////////////////////////////////////////////////////////////////////////

module data_mem #(
    parameter int DEPTH = 1024,
    parameter int WIDTH = 32
)(
    input  logic            clk,
    input  logic            reset_n,
    input  logic            mem_write,
    input  logic [31:0]     addr,
    input  logic [WIDTH-1:0] wdata,
    output logic [WIDTH-1:0] rdata
);
    logic [WIDTH-1:0] mem [0:DEPTH-1];
    
    always_ff @(posedge clk or negedge reset_n) begin
        if (!reset_n) begin
             for (int i = 0; i < DEPTH; i++) begin
                 mem[i] <= '0;
             end
        end
        else begin
            if (mem_write) begin
                mem[addr[31:2]] <= wdata;
            end
        end
    end
    
    assign rdata = mem[addr[31:2]];
endmodule

Computer_Architecture/Labs/Lab06/Adnan_alqarawi/rtl/alu.sv
`timescale 1ns / 1ps
//////////////////////////////////////////////////////////////////////////////////
// Company: 
// Engineer: 
// 
// Create Date: 12/25/2024 04:39:24 PM
// Design Name: 
// Module Name: alu
// Project Name: 
// Target Devices: 
// Tool Versions: 
// Description: 
// 
// Dependencies: 
// 
// Revision:
// Revision 0.01 - File Created
// Additional Comments:
// 
//////////////////////////////////////////////////////////////////////////////////


module alu(
    input logic [31:0] op1,
    input logic [31:0] op2,
    input logic [3:0] alu_ctr,
    output logic zero,
    output logic [31 :0 ] alu_resul
    );
    
    always_comb begin 
        case (alu_ctr) 
            4'b0000: alu_resul = op1 + op2;
            4'b1000: alu_resul = op1 - op2;
            4'b0001: alu_resul = op1 << op2[4:0];
            4'b0101: alu_resul = op1 >> op2[4:0];
            4'b1101: alu_resul = $signed(op1) >>> op2[4:0];
            4'b0111: alu_resul = op1 & op2;
            4'b0110: alu_resul = op1 | op2;
            4'b0100: alu_resul = op1 ^ op2;
            4'b0010: alu_resul = ($signed(op1) < $signed(op2)) ? 32'h1 : 32'h0;
            4'b0011: alu_resul = (op1 < op2) ? 32'h1 : 32'h0;
            default: alu_resul = 32'h0;
        endcase
        
        
    end
    
    assign zero = ~(|alu_resul);
    
    
    
endmodule

Computer_Architecture/Labs/Lab06/Adnan_alqarawi/rtl/rtl.srcs/sources_1/new/reg_file.sv
`timescale 1ns / 1ps
//////////////////////////////////////////////////////////////////////////////////
// Company: 
// Engineer: 
// 
// Create Date: 12/25/2024 03:02:17 PM
// Design Name: 
// Module Name: reg_file
// Project Name: 
// Target Devices: 
// Tool Versions: 
// Description: 
// 
// Dependencies: 
// 
// Revision:
// Revision 0.01 - File Created
// Additional Comments:
// 
//////////////////////////////////////////////////////////////////////////////////


module reg_file(
    input logic clk,
    input logic reset_n,
    input logic reg_write,
    input logic [4:0] raddr1,
    input logic [4:0] raddr2,
    input logic [4:0] waddr,
    input logic [31:0] wdata,
    output logic [31:0] rdata1,
    output logic [31:0] rdata2
    );
    
    logic [31:0] registers [31:0];
    
    always@(posedge clk, negedge reset_n) begin 
        if (~reset_n) begin
           for (int i = 0; i < 32; i++) begin
              registers[i] <= 32'h00000000;
            end
         end
           else  begin 
           if (reg_write) begin 
            registers[waddr] <= wdata;
           end    
       end
    end
    
    
    assign rdata1 = registers [raddr1];
    assign rdata2 = registers [raddr2];

endmodule

Computer_Architecture/Labs/Lab06/Adnan_alqarawi/rtl/rtl.srcs/sources_1/new/alu_controller.sv
`timescale 1ns / 1ps
//////////////////////////////////////////////////////////////////////////////////
// Company: 
// Engineer: 
// 
// Create Date: 12/25/2024 05:07:00 PM
// Design Name: 
// Module Name: alu_controller
// Project Name: 
// Target Devices: 
// Tool Versions: 
// Description: 
// 
// Dependencies: 
// 
// Revision:
// Revision 0.01 - File Created
// Additional Comments:
// 
//////////////////////////////////////////////////////////////////////////////////

module alu_control (
    input  logic [1:0]  alu_op,
    input  logic [6:0]  fun7,
    input  logic [2:0]  fun3,
    output logic [3:0]  alu_ctrl
);

    always_comb begin
        alu_ctrl = 4'b0000; 

        case (alu_op)
           //load and store
            2'b00: begin
                alu_ctrl = 4'b0000; 
            end

            // branches 
            2'b01: begin
                alu_ctrl = 4'b1000; 
            end

            // R type 
            2'b10: begin
                alu_ctrl = { fun7[5], fun3 };
            end

            // I type 
            2'b11: begin
                alu_ctrl = { fun7[5], fun3 };
            end
        endcase
    end

endmodule

Computer_Architecture/Labs/Lab06/Adnan_alqarawi/rtl/imm_gen.sv
`timescale 1ns / 1ps
//////////////////////////////////////////////////////////////////////////////////
// Company: 
// Engineer: 
// 
// Create Date: 12/25/2024 09:00:30 PM
// Design Name: 
// Module Name: imm_gen
// Project Name: 
// Target Devices: 
// Tool Versions: 
// Description: 
// 
// Dependencies: 
// 
// Revision:
// Revision 0.01 - File Created
// Additional Comments:
// 
//////////////////////////////////////////////////////////////////////////////////


module imm_gen(
    input logic [31:0] inst,
    output logic [31:0]imm
    );
    
    logic [6:0] opcode; 
    
    always_comb begin 
        opcode = inst [6:0];
        imm = 32'd0;
        
        case(opcode)
            
            7'b0000011,
            7'b0010011: begin
                imm = { {20{inst[31]}}, inst[31:20] };
            end
            7'b1100011: begin
                imm = { {19{inst[31]}}, inst[31], inst[7], inst[30:25], inst[11:8], 1'b0 };
            end
            7'b0100011: begin 
                imm = { {20{inst[31]}}, inst[31:25], inst[11:7]};  
            end 
            default: begin
                imm = 32'd0;
          
            end 
        endcase
    
    end 
    
    
endmodule

Computer_Architecture/Labs/Lab06/Adnan_alqarawi/rtl/main_control.sv
`timescale 1ns / 1ps
//////////////////////////////////////////////////////////////////////////////////
// Company: 
// Engineer: 
// 
// Create Date: 12/26/2024 01:01:10 PM
// Design Name: 
// Module Name: main_control
// Project Name: 
// Target Devices: 
// Tool Versions: 
// Description: 
// 
// Dependencies: 
// 
// Revision:
// Revision 0.01 - File Created
// Additional Comments:
// 
//////////////////////////////////////////////////////////////////////////////////



module main_control(
    input  logic [6:0] opcode,
    output logic       reg_write,
    output logic       mem_write,
    output logic       mem_to_reg,
    output logic [1:0] alu_op,
    output logic       alu_src,
    output logic       branch
);

    always_comb begin
        reg_write  = 0;
        mem_write  = 0;
        mem_to_reg = 0;
        alu_op     = 2'b00;
        alu_src    = 0;
        branch     = 0;

        case (opcode)
           
            7'b0110011: begin
                reg_write  = 1;
                mem_write  = 0;
                mem_to_reg = 0;
                alu_op     = 2'b10;  
                alu_src    = 0;
                branch     = 0;
            end

           
            7'b0010011: begin
                reg_write  = 1;
                mem_write  = 0;
                mem_to_reg = 0;
                alu_op     = 2'b11;  
                alu_src    = 1;
                branch     = 0;
            end

           
            7'b0000011: begin
                reg_write  = 1;
                mem_write  = 0;
                mem_to_reg = 1;
                alu_op     = 2'b00;
                alu_src    = 1;
                branch     = 0;
            end

           
            7'b0100011: begin
                reg_write  = 0;
                mem_write  = 1;
                mem_to_reg = 1'bx; 
                alu_op     = 2'b00;
                alu_src    = 1;
                branch     = 0;
            end
            
            7'b1100011: begin
                reg_write  = 0;
                mem_write  = 0;
                mem_to_reg = 1'bx; 
                alu_op     = 2'b01;
                alu_src    = 0;
                branch     = 1;
            end

            // Default (unrecognized opcode)
            default: begin
                reg_write  = 0;
                mem_write  = 0;
                mem_to_reg = 0;
                alu_op     = 2'b00;
                alu_src    = 0;
                branch     = 0;
            end
        endcase
    end

endmodule

Computer_Architecture/Labs/Lab06/Adnan_alqarawi/rtl/rtl.srcs/sources_1/new/inst_mem.sv
`timescale 1ns / 1ps
//////////////////////////////////////////////////////////////////////////////////
// Company: 
// Engineer: 
// 
// Create Date: 12/24/2024 10:56:40 PM
// Design Name: 
// Module Name: inst_mem
// Project Name: 
// Target Devices: 
// Tool Versions: 
// Description: 
// 
// Dependencies: 
// 
// Revision:
// Revision 0.01 - File Created
// Additional Comments:
// 
//////////////////////////////////////////////////////////////////////////////////


module inst_mem(
    input  logic [31:0] address,
    output logic [31:0] instruction
);
    logic [31:0] memory [0:255];

    initial begin
        $readmemh("/home/it/machine.hex", memory);
    end

    assign instruction = memory[address[31:2]];

endmodule

Computer_Architecture/Labs/Lab06/Adnan_alqarawi/rtl/rtl.srcs/sources_1/new/program_counter.sv
`timescale 1ns / 1ps
//////////////////////////////////////////////////////////////////////////////////
// Company: 
// Engineer: 
// 
// Create Date: 12/24/2024 10:48:13 PM
// Design Name: 
// Module Name: program_counter
// Project Name: 
// Target Devices: 
// Tool Versions: 
// Description: 
// 
// Dependencies: 
// 
// Revision:
// Revision 0.01 - File Created
// Additional Comments:
// 
//////////////////////////////////////////////////////////////////////////////////


module program_counter #(
    parameter int n = 32  
)(
    input  logic            clk,
    input  logic            reset_n,      
    input  logic [n-1:0]    data_in,      
    output logic [n-1:0]    data_o        
);

    
    always_ff @(posedge clk or negedge reset_n) begin
        if (!reset_n) begin
            data_o <= '0;  
        end
        else begin
            data_o <= data_in;
        end
    end

endmodule

Computer_Architecture/Labs/Lab06/Adnan_alqarawi/rtl/rtl.srcs/sources_1/new/rv32i_top.sv
`timescale 1ns/1ps

module rv32i_top(
    input  logic clk,
    input  logic reset_n
);

    logic [31:0] pc;
    logic [31:0] next_pc;
    logic [31:0] instruction;
    logic [31:0] imm;
    logic [31:0] reg_read_data1, reg_read_data2;
    logic [31:0] alu_result;
    logic [31:0] mem_read_data;
    logic [3:0]  alu_ctrl;
    logic [6:0]  funct7;
    logic [2:0]  funct3;
    logic [6:0]  opcode;
    logic [4:0]  rs1, rs2, rd;
    logic        zero;
    logic        reg_write, mem_write, mem_to_reg, alu_src, branch;
    logic [1:0]  alu_op;

    program_counter pc_inst (
        .clk     (clk),
        .reset_n (reset_n),
        .data_in (next_pc),
        .data_o  (pc)
    );

    inst_mem imem (
        .address     (pc),
        .instruction (instruction)
    );

    assign opcode = instruction[6:0];
    assign rd     = instruction[11:7];
    assign funct3 = instruction[14:12];
    assign rs1    = instruction[19:15];
    assign rs2    = instruction[24:20];
    assign funct7 = instruction[31:25];

    main_control ctrl (
        .opcode     (opcode),
        .reg_write  (reg_write),
        .mem_write  (mem_write),
        .mem_to_reg (mem_to_reg),
        .alu_op     (alu_op),
        .alu_src    (alu_src),
        .branch     (branch)
    );

    imm_gen immg (
        .inst (instruction),
        .imm  (imm)
    );

    alu_control alu_ctrl_unit (
        .alu_op   (alu_op),
        .fun7     (funct7),
        .fun3     (funct3),
        .alu_ctrl (alu_ctrl)
    );

    logic [31:0] reg_write_data;
    reg_file regs (
        .clk       (clk),
        .reset_n   (reset_n),
        .reg_write (reg_write),
        .raddr1    (rs1),
        .raddr2    (rs2),
        .waddr     (rd),
        .wdata     (reg_write_data),
        .rdata1    (reg_read_data1),
        .rdata2    (reg_read_data2)
    );

    logic [31:0] alu_operand2;
    assign alu_operand2 = (alu_src) ? imm : reg_read_data2;

    alu alu_inst (
        .op1      (reg_read_data1),
        .op2      (alu_operand2),
        .alu_ctr  (alu_ctrl),
        .zero     (zero),
        .alu_resul(alu_result)
    );

    data_mem dmem (
        .clk       (clk),
        .reset_n   (reset_n),
        .mem_write (mem_write),
        .addr      (alu_result),
        .wdata     (reg_read_data2),
        .rdata     (mem_read_data)
    );

    assign reg_write_data = (mem_to_reg) ? mem_read_data : alu_result;

    logic [31:0] pc_plus_4;
    assign pc_plus_4 = pc + 4;
    assign next_pc   = (branch & zero) ? (pc + imm) : pc_plus_4;

endmodule

Computer_Architecture/Labs/Lab06/Adnan_alqarawi/rtl/rtl.srcs/sim_1/new/tb_rv32i_top.sv
`timescale 1ns / 1ps
//////////////////////////////////////////////////////////////////////////////////
// Company: 
// Engineer: 
// 
// Create Date: 12/29/2024 03:21:26 PM
// Design Name: 
// Module Name: tb_rv32i_top
// Project Name: 
// Target Devices: 
// Tool Versions: 
// Description: 
// 
// Dependencies: 
// 
// Revision:
// Revision 0.01 - File Created
// Additional Comments:
// 
//////////////////////////////////////////////////////////////////////////////////


`timescale 1ns/1ps

module tb_rv32i_top;

    logic clk;
    logic reset_n;

    // Instantiate your top-level CPU
    rv32i_top dut (
        .clk     (clk),
        .reset_n (reset_n)
    );

    // Clock generation: toggle clk every 5 ns (100 MHz)
    initial begin
        clk = 0;
        forever #5 clk = ~clk;
    end

    // Reset: hold low for 20 ns, then go high
    initial begin
        reset_n = 1'b0;
        #20;
        reset_n = 1'b1;
    end

    // Initialize instruction memory with program.hex (optional)
    // If your top module or inst_mem module does $readmemh internally,
    // you can omit this block or adapt it to match your design.
    initial begin
        // If dut.imem.memory is publicly visible, do:
        // $readmemh("machine.hex", dut.imem.memory);
        // Otherwise, if your inst_mem module has $readmemh inside it,
        // this step is not needed here.
        #0;
    end

    // Run simulation for a fixed time, then finish
    initial begin
        #10000; // e.g. run for 10,000 ns
        $finish;
    end

    // Optional waveform dump
    initial begin
        $dumpfile("tb_rv32i_top.vcd");
        $dumpvars(0, tb_rv32i_top);
    end

endmodule

Computer_Architecture/Labs/Lab06/Adnan_alqarawi/rtl/rtl.sim/sim_1/behav/xsim/tb_rv32i_top.vcd
$date
   Sun Dec 29 15:45:18 2024
$end
$version
  2019.1
$end
$timescale
  1ps
$end
$scope module tb_rv32i_top $end
$var reg 1 ! clk $end
$var reg 1 " reset_n $end
$scope module dut $end
$var wire 1 # clk $end
$var wire 1 $ reset_n $end
$var reg 32 % pc [31:0] $end
$var reg 32 & next_pc [31:0] $end
$var reg 32 ' instruction [31:0] $end
$var reg 32 ( imm [31:0] $end
$var reg 32 ) reg_read_data1 [31:0] $end
$var reg 32 * reg_read_data2 [31:0] $end
$var reg 32 + alu_result [31:0] $end
$var reg 32 , mem_read_data [31:0] $end
$var reg 4 - alu_ctrl [3:0] $end
$var reg 7 . funct7 [6:0] $end
$var reg 3 / funct3 [2:0] $end
$var reg 7 0 opcode [6:0] $end
$var reg 5 1 rs1 [4:0] $end
$var reg 5 2 rs2 [4:0] $end
$var reg 5 3 rd [4:0] $end
$var reg 1 4 zero $end
$var reg 1 5 reg_write $end
$var reg 1 6 mem_write $end
$var reg 1 7 mem_to_reg $end
$var reg 1 8 alu_src $end
$var reg 1 9 branch $end
$var reg 2 : alu_op [1:0] $end
$var reg 32 ; reg_write_data [31:0] $end
$var reg 32 < alu_operand2 [31:0] $end
$var reg 32 = pc_plus_4 [31:0] $end
$scope module pc_inst $end
$var wire 1 # clk $end
$var wire 1 $ reset_n $end
$var wire 32 > data_in [31:0] $end
$var reg 32 % data_o [31:0] $end
$var parameter 0 ? n $end
$upscope $end
$scope module imem $end
$var wire 32 @ address [31:0] $end
$var reg 32 ' instruction [31:0] $end
$upscope $end
$scope module ctrl $end
$var wire 7 A opcode [6:0] $end
$var reg 1 5 reg_write $end
$var reg 1 6 mem_write $end
$var reg 1 7 mem_to_reg $end
$var reg 2 : alu_op [1:0] $end
$var reg 1 8 alu_src $end
$var reg 1 9 branch $end
$upscope $end
$scope module immg $end
$var wire 32 B inst [31:0] $end
$var reg 32 ( imm [31:0] $end
$var reg 7 C opcode [6:0] $end
$upscope $end
$scope module alu_ctrl_unit $end
$var wire 2 D alu_op [1:0] $end
$var wire 7 E fun7 [6:0] $end
$var wire 3 F fun3 [2:0] $end
$var reg 4 - alu_ctrl [3:0] $end
$upscope $end
$scope module regs $end
$var wire 1 # clk $end
$var wire 1 $ reset_n $end
$var wire 1 G reg_write $end
$var wire 5 H raddr1 [4:0] $end
$var wire 5 I raddr2 [4:0] $end
$var wire 5 J waddr [4:0] $end
$var wire 32 K wdata [31:0] $end
$var reg 32 ) rdata1 [31:0] $end
$var reg 32 * rdata2 [31:0] $end
$scope begin Block39_6 $end
$var reg 32 L i $end
$upscope $end
$upscope $end
$scope module alu_inst $end
$var wire 32 M op1 [31:0] $end
$var wire 32 N op2 [31:0] $end
$var wire 4 O alu_ctr [3:0] $end
$var reg 1 4 zero $end
$var reg 32 + alu_resul [31:0] $end
$upscope $end
$scope module dmem $end
$var wire 1 # clk $end
$var wire 1 $ reset_n $end
$var wire 1 P mem_write $end
$var wire 32 Q addr [31:0] $end
$var wire 32 R wdata [31:0] $end
$var reg 32 , rdata [31:0] $end
$var parameter 0 S DEPTH $end
$var parameter 0 T WIDTH $end
$scope begin Block37_9 $end
$var reg 32 U i $end
$upscope $end
$upscope $end
$upscope $end
$upscope $end
$enddefinitions $end
#0
$dumpvars
0!
0"
0#
0$
b0 %
b100 &
b10100000000000010010011 '
b101 (
b0 )
b0 *
b101 +
b0 ,
b0 -
b0 .
b0 /
b10011 0
b0 1
b101 2
b1 3
04
15
06
07
18
09
b11 :
b101 ;
b101 <
b100 =
b100 >
b100000 ?
b0 @
b10011 A
b10100000000000010010011 B
b10011 C
b11 D
b0 E
b0 F
1G
b0 H
b101 I
b1 J
b101 K
b0 L
b0 M
b101 N
b0 O
0P
b101 Q
b0 R
b10000000000 S
b100000 T
b10000000000 U
$end
#5000
1!
1#
b10000000000 U
#10000
0!
0#
#15000
1!
1#
b10000000000 U
#20000
0!
1"
0#
1$
#25000
1!
1#
b100 %
b1000 &
b101000000000000100010011 '
b1010 (
b0 )
b0 *
b1010 +
b0 ,
b1010 2
b10 3
04
b1010 ;
b1010 <
b1000 =
b1000 >
b100 @
b101000000000000100010011 B
b10011 C
b1010 I
b10 J
b1010 K
b1010 N
b1010 Q
#30000
0!
0#
#35000
1!
1#
b1000 %
b1100 &
b1000001000000110110011 '
b0 (
b101 )
b1010 *
b1111 +
b0 ,
b0 -
b110011 0
b1 1
b10 2
b11 3
04
15
06
07
08
09
b10 :
b1111 ;
b1010 <
b1100 =
b1100 >
b1000 @
b110011 A
b1000001000000110110011 B
b110011 C
b10 D
b1 H
b10 I
b11 J
b1111 K
b101 M
b1010 N
b1111 Q
b1010 R
#40000
0!
0#
#45000
1!
1#
b1100 %
b10000 &
b11111111111100011100000110010011 '
b11111111111111111111111111111111 (
b1111 )
b0 *
b0 +
b0 ,
b1100 -
b1111111 .
b100 /
b10011 0
b11 1
b11111 2
14
15
06
07
18
09
b11 :
b0 ;
b11111111111111111111111111111111 <
b10000 =
b10000 >
b1100 @
b10011 A
b11111111111100011100000110010011 B
b10011 C
b11 D
b1111111 E
b100 F
b11 H
b11111 I
b0 K
b1111 M
b11111111111111111111111111111111 N
b1100 O
b0 Q
b0 R
#50000
0!
0#
#55000
1!
1#
b10000 %
b1100 &
b11111110000001110001111011100011 '
b11111111111111111111111111111100 (
b0 )
b0 *
b0 +
b1000 -
b1 /
b1100011 0
b1110 1
b0 2
b11101 3
05
06
x7
08
19
b1 :
b0 ;
b0 <
b10100 =
b1100 >
b10000 @
b1100011 A
b11111110000001110001111011100011 B
b1100011 C
b1 D
b1 F
0G
b1110 H
b0 I
b11101 J
b0 M
b0 N
b1000 O
#60000
0!
0#
#65000
1!
1#
b1100 %
b10000 &
b11111111111100011100000110010011 '
b11111111111111111111111111111111 (
b0 )
b0 *
b0 +
b1100 -
b100 /
b10011 0
b11 1
b11111 2
b11 3
15
06
07
18
09
b11 :
b0 ;
b11111111111111111111111111111111 <
b10000 =
b10000 >
b1100 @
b10011 A
b11111111111100011100000110010011 B
b10011 C
b11 D
b100 F
1G
b11 H
b11111 I
b11 J
b11111111111111111111111111111111 N
b1100 O
#70000
0!
0#
#75000
1!
1#
b10000 %
b1100 &
b11111110000001110001111011100011 '
b11111111111111111111111111111100 (
b0 )
b0 *
b0 +
b1000 -
b1 /
b1100011 0
b1110 1
b0 2
b11101 3
05
06
x7
08
19
b1 :
b0 ;
b0 <
b10100 =
b1100 >
b10000 @
b1100011 A
b11111110000001110001111011100011 B
b1100011 C
b1 D
b1 F
0G
b1110 H
b0 I
b11101 J
b0 N
b1000 O
#80000
0!
0#
#85000
1!
1#
b1100 %
b10000 &
b11111111111100011100000110010011 '
b11111111111111111111111111111111 (
b0 )
b0 *
b0 +
b1100 -
b100 /
b10011 0
b11 1
b11111 2
b11 3
15
06
07
18
09
b11 :
b0 ;
b11111111111111111111111111111111 <
b10000 =
b10000 >
b1100 @
b10011 A
b11111111111100011100000110010011 B
b10011 C
b11 D
b100 F
1G
b11 H
b11111 I
b11 J
b11111111111111111111111111111111 N
b1100 O
#90000
0!
0#
#95000
1!
1#
b10000 %
b1100 &
b11111110000001110001111011100011 '
b11111111111111111111111111111100 (
b0 )
b0 *
b0 +
b1000 -
b1 /
b1100011 0
b1110 1
b0 2
b11101 3
05
06
x7
08
19
b1 :
b0 ;
b0 <
b10100 =
b1100 >
b10000 @
b1100011 A
b11111110000001110001111011100011 B
b1100011 C
b1 D
b1 F
0G
b1110 H
b0 I
b11101 J
b0 N
b1000 O
#100000
0!
0#
#105000
1!
1#
b1100 %
b10000 &
b11111111111100011100000110010011 '
b11111111111111111111111111111111 (
b0 )
b0 *
b0 +
b1100 -
b100 /
b10011 0
b11 1
b11111 2
b11 3
15
06
07
18
09
b11 :
b0 ;
b11111111111111111111111111111111 <
b10000 =
b10000 >
b1100 @
b10011 A
b11111111111100011100000110010011 B
b10011 C
b11 D
b100 F
1G
b11 H
b11111 I
b11 J
b11111111111111111111111111111111 N
b1100 O
#110000
0!
0#
#115000
1!
1#
b10000 %
b1100 &
b11111110000001110001111011100011 '
b11111111111111111111111111111100 (
b0 )
b0 *
b0 +
b1000 -
b1 /
b1100011 0
b1110 1
b0 2
b11101 3
05
06
x7
08
19
b1 :
b0 ;
b0 <
b10100 =
b1100 >
b10000 @
b1100011 A
b11111110000001110001111011100011 B
b1100011 C
b1 D
b1 F
0G
b1110 H
b0 I
b11101 J
b0 N
b1000 O
#120000
0!
0#
#125000
1!
1#
b1100 %
b10000 &
b11111111111100011100000110010011 '
b11111111111111111111111111111111 (
b0 )
b0 *
b0 +
b1100 -
b100 /
b10011 0
b11 1
b11111 2
b11 3
15
06
07
18
09
b11 :
b0 ;
b11111111111111111111111111111111 <
b10000 =
b10000 >
b1100 @
b10011 A
b11111111111100011100000110010011 B
b10011 C
b11 D
b100 F
1G
b11 H
b11111 I
b11 J
b11111111111111111111111111111111 N
b1100 O
#130000
0!
0#
#135000
1!
1#
b10000 %
b1100 &
b11111110000001110001111011100011 '
b11111111111111111111111111111100 (
b0 )
b0 *
b0 +
b1000 -
b1 /
b1100011 0
b1110 1
b0 2
b11101 3
05
06
x7
08
19
b1 :
b0 ;
b0 <
b10100 =
b1100 >
b10000 @
b1100011 A
b11111110000001110001111011100011 B
b1100011 C
b1 D
b1 F
0G
b1110 H
b0 I
b11101 J
b0 N
b1000 O
#140000
0!
0#
#145000
1!
1#
b1100 %
b10000 &
b11111111111100011100000110010011 '
b11111111111111111111111111111111 (
b0 )
b0 *
b0 +
b1100 -
b100 /
b10011 0
b11 1
b11111 2
b11 3
15
06
07
18
09
b11 :
b0 ;
b11111111111111111111111111111111 <
b10000 =
b10000 >
b1100 @
b10011 A
b11111111111100011100000110010011 B
b10011 C
b11 D
b100 F
1G
b11 H
b11111 I
b11 J
b11111111111111111111111111111111 N
b1100 O
#150000
0!
0#
#155000
1!
1#
b10000 %
b1100 &
b11111110000001110001111011100011 '
b11111111111111111111111111111100 (
b0 )
b0 *
b0 +
b1000 -
b1 /
b1100011 0
b1110 1
b0 2
b11101 3
05
06
x7
08
19
b1 :
b0 ;
b0 <
b10100 =
b1100 >
b10000 @
b1100011 A
b11111110000001110001111011100011 B
b1100011 C
b1 D
b1 F
0G
b1110 H
b0 I
b11101 J
b0 N
b1000 O
#160000
0!
0#
#165000
1!
1#
b1100 %
b10000 &
b11111111111100011100000110010011 '
b11111111111111111111111111111111 (
b0 )
b0 *
b0 +
b1100 -
b100 /
b10011 0
b11 1
b11111 2
b11 3
15
06
07
18
09
b11 :
b0 ;
b11111111111111111111111111111111 <
b10000 =
b10000 >
b1100 @
b10011 A
b11111111111100011100000110010011 B
b10011 C
b11 D
b100 F
1G
b11 H
b11111 I
b11 J
b11111111111111111111111111111111 N
b1100 O
#170000
0!
0#
#175000
1!
1#
b10000 %
b1100 &
b11111110000001110001111011100011 '
b11111111111111111111111111111100 (
b0 )
b0 *
b0 +
b1000 -
b1 /
b1100011 0
b1110 1
b0 2
b11101 3
05
06
x7
08
19
b1 :
b0 ;
b0 <
b10100 =
b1100 >
b10000 @
b1100011 A
b11111110000001110001111011100011 B
b1100011 C
b1 D
b1 F
0G
b1110 H
b0 I
b11101 J
b0 N
b1000 O
#180000
0!
0#
#185000
1!
1#
b1100 %
b10000 &
b11111111111100011100000110010011 '
b11111111111111111111111111111111 (
b0 )
b0 *
b0 +
b1100 -
b100 /
b10011 0
b11 1
b11111 2
b11 3
15
06
07
18
09
b11 :
b0 ;
b11111111111111111111111111111111 <
b10000 =
b10000 >
b1100 @
b10011 A
b11111111111100011100000110010011 B
b10011 C
b11 D
b100 F
1G
b11 H
b11111 I
b11 J
b11111111111111111111111111111111 N
b1100 O
#190000
0!
0#
#195000
1!
1#
b10000 %
b1100 &
b11111110000001110001111011100011 '
b11111111111111111111111111111100 (
b0 )
b0 *
b0 +
b1000 -
b1 /
b1100011 0
b1110 1
b0 2
b11101 3
05
06
x7
08
19
b1 :
b0 ;
b0 <
b10100 =
b1100 >
b10000 @
b1100011 A
b11111110000001110001111011100011 B
b1100011 C
b1 D
b1 F
0G
b1110 H
b0 I
b11101 J
b0 N
b1000 O
#200000
0!
0#
#205000
1!
1#
b1100 %
b10000 &
b11111111111100011100000110010011 '
b11111111111111111111111111111111 (
b0 )
b0 *
b0 +
b1100 -
b100 /
b10011 0
b11 1
b11111 2
b11 3
15
06
07
18
09
b11 :
b0 ;
b11111111111111111111111111111111 <
b10000 =
b10000 >
b1100 @
b10011 A
b11111111111100011100000110010011 B
b10011 C
b11 D
b100 F
1G
b11 H
b11111 I
b11 J
b11111111111111111111111111111111 N
b1100 O
#210000
0!
0#
#215000
1!
1#
b10000 %
b1100 &
b11111110000001110001111011100011 '
b11111111111111111111111111111100 (
b0 )
b0 *
b0 +
b1000 -
b1 /
b1100011 0
b1110 1
b0 2
b11101 3
05
06
x7
08
19
b1 :
b0 ;
b0 <
b10100 =
b1100 >
b10000 @
b1100011 A
b11111110000001110001111011100011 B
b1100011 C
b1 D
b1 F
0G
b1110 H
b0 I
b11101 J
b0 N
b1000 O
#220000
0!
0#
#225000
1!
1#
b1100 %
b10000 &
b11111111111100011100000110010011 '
b11111111111111111111111111111111 (
b0 )
b0 *
b0 +
b1100 -
b100 /
b10011 0
b11 1
b11111 2
b11 3
15
06
07
18
09
b11 :
b0 ;
b11111111111111111111111111111111 <
b10000 =
b10000 >
b1100 @
b10011 A
b11111111111100011100000110010011 B
b10011 C
b11 D
b100 F
1G
b11 H
b11111 I
b11 J
b11111111111111111111111111111111 N
b1100 O
#230000
0!
0#
#235000
1!
1#
b10000 %
b1100 &
b11111110000001110001111011100011 '
b11111111111111111111111111111100 (
b0 )
b0 *
b0 +
b1000 -
b1 /
b1100011 0
b1110 1
b0 2
b11101 3
05
06
x7
08
19
b1 :
b0 ;
b0 <
b10100 =
b1100 >
b10000 @
b1100011 A
b11111110000001110001111011100011 B
b1100011 C
b1 D
b1 F
0G
b1110 H
b0 I
b11101 J
b0 N
b1000 O
#240000
0!
0#
#245000
1!
1#
b1100 %
b10000 &
b11111111111100011100000110010011 '
b11111111111111111111111111111111 (
b0 )
b0 *
b0 +
b1100 -
b100 /
b10011 0
b11 1
b11111 2
b11 3
15
06
07
18
09
b11 :
b0 ;
b11111111111111111111111111111111 <
b10000 =
b10000 >
b1100 @
b10011 A
b11111111111100011100000110010011 B
b10011 C
b11 D
b100 F
1G
b11 H
b11111 I
b11 J
b11111111111111111111111111111111 N
b1100 O
#250000
0!
0#
#255000
1!
1#
b10000 %
b1100 &
b11111110000001110001111011100011 '
b11111111111111111111111111111100 (
b0 )
b0 *
b0 +
b1000 -
b1 /
b1100011 0
b1110 1
b0 2
b11101 3
05
06
x7
08
19
b1 :
b0 ;
b0 <
b10100 =
b1100 >
b10000 @
b1100011 A
b11111110000001110001111011100011 B
b1100011 C
b1 D
b1 F
0G
b1110 H
b0 I
b11101 J
b0 N
b1000 O
#260000
0!
0#
#265000
1!
1#
b1100 %
b10000 &
b11111111111100011100000110010011 '
b11111111111111111111111111111111 (
b0 )
b0 *
b0 +
b1100 -
b100 /
b10011 0
b11 1
b11111 2
b11 3
15
06
07
18
09
b11 :
b0 ;
b11111111111111111111111111111111 <
b10000 =
b10000 >
b1100 @
b10011 A
b11111111111100011100000110010011 B
b10011 C
b11 D
b100 F
1G
b11 H
b11111 I
b11 J
b11111111111111111111111111111111 N
b1100 O
#270000
0!
0#
#275000
1!
1#
b10000 %
b1100 &
b11111110000001110001111011100011 '
b11111111111111111111111111111100 (
b0 )
b0 *
b0 +
b1000 -
b1 /
b1100011 0
b1110 1
b0 2
b11101 3
05
06
x7
08
19
b1 :
b0 ;
b0 <
b10100 =
b1100 >
b10000 @
b1100011 A
b11111110000001110001111011100011 B
b1100011 C
b1 D
b1 F
0G
b1110 H
b0 I
b11101 J
b0 N
b1000 O
#280000
0!
0#
#285000
1!
1#
b1100 %
b10000 &
b11111111111100011100000110010011 '
b11111111111111111111111111111111 (
b0 )
b0 *
b0 +
b1100 -
b100 /
b10011 0
b11 1
b11111 2
b11 3
15
06
07
18
09
b11 :
b0 ;
b11111111111111111111111111111111 <
b10000 =
b10000 >
b1100 @
b10011 A
b11111111111100011100000110010011 B
b10011 C
b11 D
b100 F
1G
b11 H
b11111 I
b11 J
b11111111111111111111111111111111 N
b1100 O
#290000
0!
0#
